README.md
setup.py
dimond/__init__.py
dimond.egg-info/PKG-INFO
dimond.egg-info/SOURCES.txt
dimond.egg-info/dependency_links.txt
dimond.egg-info/not-zip-safe
dimond.egg-info/requires.txt
dimond.egg-info/top_level.txt